examples/__init__.py
examples/example_usage.py
insta360_gfpt/__init__.py
insta360_gfpt/cli.py
insta360_gfpt/main.py
insta360_gfpt/utils.py
insta360_gfpt/templates/main.py
insta360_gfpt/templates/setting.json
insta360_gfpt/templates/res/qml/main.qml
insta360_gfpt/templates/res/qml/control/InsButton.qml
insta360_gfpt/templates/res/qml/control/InsCheckBox.qml
insta360_gfpt/templates/res/qml/control/InsCombox.qml
insta360_gfpt/templates/res/qml/control/InsImage.qml
insta360_gfpt/templates/res/qml/control/InsLabel.qml
insta360_gfpt/templates/res/qml/control/InsLocalImage.qml
insta360_gfpt/templates/res/qml/control/InsMessageDialog.qml
insta360_gfpt/templates/res/qml/control/InsSettingDialog.qml
insta360_gfpt/templates/res/qml/control/InsText.qml
insta360_gfpt/templates/res/qml/control/InsTextField.qml
insta360_gfpt/templates/res/qml/control/InsVideo.qml
insta360_gfpt/templates/res/qml/panel/ControlBar.qml
insta360_gfpt/templates/res/qml/panel/DeviceInfoPanel.qml
insta360_gfpt/templates/res/qml/panel/DeviceListPanel.qml
insta360_gfpt/templates/res/qml/panel/InsMenuBar.qml
insta360_gfpt/templates/res/qml/panel/TestList.qml
insta360_gfpt/templates/res/qml/panel/TestModule.qml
insta360_gfpt/templates/res/qml/panel/Version.qml
insta360_gfpt/templates/res/qml/special/CustomImg.qml
insta360_gfpt/templates/res/qml/special/CustomLocalImg.qml
insta360_gfpt/templates/res/qml/special/CustomVideo.qml
insta360_gfpt/templates/res/qml/special/DeviceItem.qml
insta360_gfpt/templates/res/qml/special/PasswordDlg.qml
insta360_gfpt/templates/res/qml/special/ResLabel.qml
insta360_gfpt/templates/res/qml/special/ResPopup.qml
insta360_gfpt/templates/res/qml/special/StationPopup.qml
insta360_gfpt/templates/res/qml/special/TestItem.qml
insta360_gfpt/templates/res/qml/special/TestResList.qml
insta360_gfpt/templates/res/qml/special/UnderLineLabel.qml
insta360_gfpt/templates/res/qml/unit/IAC2/age_result_test_unit.qml
insta360_gfpt/templates/res/qml/unit/IAC2/age_test_unit.qml
insta360_gfpt-0.2.0.dist-info/METADATA
insta360_gfpt-0.2.0.dist-info/WHEEL
insta360_gfpt-0.2.0.dist-info/entry_points.txt
insta360_gfpt-0.2.0.dist-info/top_level.txt
insta360_gfpt-0.2.0.dist-info/RECORD
