Metadata-Version: 2.1
Name: insta360-gfpt
Version: 0.2.0
Summary: insta360 gfpt
Home-page: https://gitlab.insta360.com/test2/production-testing-tools/insta360_gfpt.git
Author: rain
Author-email: chenrunming@insta360.com
Classifier: Programming Language :: Python :: 3
Classifier: License :: OSI Approved :: MIT License
Classifier: Operating System :: OS Independent
Requires-Python: >=3.7
Requires-Dist: altgraph (==0.17.2)
Requires-Dist: Appium-Python-Client (==1.2.0)
Requires-Dist: auto-py-to-exe (==2.22.0)
Requires-Dist: bottle (==0.12.23)
Requires-Dist: bottle-websocket (==0.2.9)
Requires-Dist: certifi (==2022.6.15)
Requires-Dist: cffi (==1.15.1)
Requires-Dist: charset-normalizer (==2.1.1)
Requires-Dist: colorama (==0.4.5)
Requires-Dist: Eel (==0.14.0)
Requires-Dist: ffmpeg-python (==0.2.0)
Requires-Dist: func-timeout (==4.3.5)
Requires-Dist: future (==0.18.2)
Requires-Dist: gevent (==21.12.0)
Requires-Dist: gevent-websocket (==0.10.1)
Requires-Dist: greenlet (==1.1.3)
Requires-Dist: idna (==3.3)
Requires-Dist: importlib-metadata (==4.12.0)
Requires-Dist: importlib-resources (==5.9.0)
Requires-Dist: libusb (==1.0.24b3)
Requires-Dist: libusb1 (==3.0.0)
Requires-Dist: loguru (==0.6.0)
Requires-Dist: modbus-tk (==1.1.2)
Requires-Dist: MouseInfo (==0.1.3)
Requires-Dist: numpy
Requires-Dist: opencv-contrib-python (==4.6.0.66)
Requires-Dist: opencv-python (==4.6.0.66)
Requires-Dist: packaging (==21.3)
Requires-Dist: pefile (==2022.5.30)
Requires-Dist: Pillow (==9.2.0)
Requires-Dist: pkg-about (==1.0.7)
Requires-Dist: protobuf (==3.17.3)
Requires-Dist: PyAutoGUI (==0.9.53)
Requires-Dist: pycparser (==2.21)
Requires-Dist: PyGetWindow (==0.0.9)
Requires-Dist: pyinstaller (==5.3)
Requires-Dist: pyinstaller-hooks-contrib (==2022.10)
Requires-Dist: PyMsgBox (==1.0.9)
Requires-Dist: pyparsing (==3.0.9)
Requires-Dist: pyperclip (==1.8.2)
Requires-Dist: PyRect (==0.2.0)
Requires-Dist: PyScreeze (==0.1.28)
Requires-Dist: pyserial (==3.5)
Requires-Dist: PySide6 (==6.3.1)
Requires-Dist: PySide6-Addons (==6.3.1)
Requires-Dist: PySide6-Essentials (==6.3.1)
Requires-Dist: pytweening (==1.0.4)
Requires-Dist: pywin32-ctypes (==0.2.0)
Requires-Dist: requests (==2.28.1)
Requires-Dist: selenium (==3.141.0)
Requires-Dist: shiboken6 (==6.3.1)
Requires-Dist: six (==1.16.0)
Requires-Dist: tomli (==2.0.1)
Requires-Dist: urllib3 (==1.26.12)
Requires-Dist: whichcraft (==0.6.1)
Requires-Dist: win32-setctime (==1.1.0)
Requires-Dist: zipp (==3.8.1)
Requires-Dist: zope.event (==4.5.0)
Requires-Dist: zope.interface (==5.4.0)
Requires-Dist: requests-toolbelt
Requires-Dist: qrcode
Requires-Dist: pywifi
Requires-Dist: comtypes
Requires-Dist: adbutils
Requires-Dist: rawpy
Requires-Dist: imageio
Requires-Dist: oss2
